{
  "criteria_note": "Tröghetsregeln (SPEC-FRAGEVAGEN.md §3, ägarbeslut 2026-07-11): en fråga ingår om den förekommer på båda institutens publicerade listor över väljarnas viktigaste frågor — Novus 'Viktigaste politiska frågan' (topp 10, någon av de två senaste mätningarna räknas) och nationella SOM-undersökningen (topp 15). Underlag v1: Novus juni 2026 (fältperiod 28 maj–3 juni, n=1361) och januari 2026, samt SOM 2025 ('Svenska trender 1986–2025', publicerad mars 2026). Frågor tas aldrig bort före valdagen — de kan markeras dormant.",
  "formulation_note": "Samtliga delfrågor verifierade och låsta 2026-07-11 (steg 1 i ops/FRAGEVAGEN-LANSERING.md): ägaren godkände frågorna; formuleringarna källkontrollerades mot dagsaktuellt rättsläge och debattläge (riksdagsbeslut, lagar i kraft, publicerade förslag) och nio omformulerades/förankrades — se DECISION_LOG 2026-07-11. Rättvisetestet i fairness_note är en dokumenterad designbedömning av formuleringens egenskaper — ingen utanför projektet tillfrågas eller har godkänt något (partier tillfrågas aldrig, §5.0). Bedömningskriterier: konkret ja/nej-besvarbar, inga värdeladdade ord, inget svar framställs som det rätta.",
  "issues": [
    {
      "id": "i-sjukvarden",
      "title": "Sjukvården",
      "slug": "sjukvarden",
      "category": "välfärd",
      "status": "aktiv",
      "selection_sources": [
        {
          "institute": "Novus",
          "survey": "Viktigaste politiska frågan, juni 2026",
          "url": "https://novus.se/valjarforstaelse-arkiv/2026-06-viktigaste-politiska-fragan/",
          "date": "2026-06-08",
          "rank": 1,
          "share_percent": 66
        },
        {
          "institute": "SOM-institutet",
          "survey": "Nationella SOM-undersökningen 2025 (Svenska trender 1986–2025)",
          "url": "https://www.gu.se/sites/default/files/2026-03/Svenska%20trender%201986-2025.pdf",
          "date": "2026-03",
          "rank": 2,
          "share_percent": 29
        }
      ],
      "subquestions": [
        {
          "id": "sq-sjukvard-huvudman",
          "text": "Ska staten ta över huvudansvaret för sjukvården från regionerna?",
          "formulation_status": "verifierad",
          "fairness_note": "Avgränsad till huvudmannaskapet (vem som ska styra vården), inte vårdens kvalitet. 'Ta över huvudansvaret' är det konkreta åtagande som skiljer positionerna, och formuleringen gör varken ja eller nej till det ansvarsfulla svaret."
        },
        {
          "id": "sq-sjukvard-vinst",
          "text": "Ska vinstuttag ur offentligt finansierad, privat driven vård begränsas i lag?",
          "formulation_status": "verifierad",
          "fairness_note": "Neutralt formulerad lagstiftningsfråga; 'begränsas i lag' avgränsar mot både fri vinst och totalförbud utan att värdera något av dem."
        }
      ]
    },
    {
      "id": "i-skolan",
      "title": "Skolan och utbildningen",
      "slug": "skolan-och-utbildningen",
      "category": "utbildning",
      "status": "aktiv",
      "selection_sources": [
        {
          "institute": "Novus",
          "survey": "Viktigaste politiska frågan, juni 2026",
          "url": "https://novus.se/valjarforstaelse-arkiv/2026-06-viktigaste-politiska-fragan/",
          "date": "2026-06-08",
          "rank": 2,
          "share_percent": 54
        },
        {
          "institute": "SOM-institutet",
          "survey": "Nationella SOM-undersökningen 2025 (Svenska trender 1986–2025)",
          "url": "https://www.gu.se/sites/default/files/2026-03/Svenska%20trender%201986-2025.pdf",
          "date": "2026-03",
          "rank": 3,
          "share_percent": 23
        }
      ],
      "subquestions": [
        {
          "id": "sq-skola-vinst",
          "text": "Ska vinstutdelning från friskolekoncerner förbjudas eller begränsas i lag?",
          "formulation_status": "verifierad",
          "fairness_note": "Skarpt avgränsad till vinstutdelning, inte friskolors existens; 'förbjudas eller begränsas' täcker båda lagstiftningslinjerna utan att värdera någon av dem."
        },
        {
          "id": "sq-skola-huvudman",
          "text": "Ska staten ta över huvudmannaskapet för skolan från kommunerna?",
          "formulation_status": "verifierad",
          "fairness_note": "Samma huvudmannaskapsram som sjukvårdsfrågan; ingen värdering av kommunal eller statlig drift."
        },
        {
          "id": "sq-skola-ko",
          "text": "Ska dagens kösystem till fristående skolor avskaffas?",
          "formulation_status": "verifierad",
          "fairness_note": "'Dagens kösystem' är en saklig beskrivning av rådande ordning, utan värdeord; frågan är rakt besvarbar med ja eller nej och antyder inte vilket svar som är det rimliga."
        }
      ]
    },
    {
      "id": "i-lag-och-ordning",
      "title": "Lag och ordning",
      "slug": "lag-och-ordning",
      "category": "rättsväsende",
      "status": "aktiv",
      "selection_sources": [
        {
          "institute": "Novus",
          "survey": "Viktigaste politiska frågan, juni 2026",
          "url": "https://novus.se/valjarforstaelse-arkiv/2026-06-viktigaste-politiska-fragan/",
          "date": "2026-06-08",
          "rank": 3,
          "share_percent": 49
        },
        {
          "institute": "SOM-institutet",
          "survey": "Nationella SOM-undersökningen 2025 (Svenska trender 1986–2025)",
          "url": "https://www.gu.se/sites/default/files/2026-03/Svenska%20trender%201986-2025.pdf",
          "date": "2026-03",
          "rank": 1,
          "share_percent": 36
        }
      ],
      "subquestions": [
        {
          "id": "sq-lag-straffalder",
          "text": "Ska straffmyndighetsåldern sänkas till 14 år för allvarliga brott?",
          "formulation_status": "verifierad",
          "fairness_note": "Förankrad i det konkreta förslaget (prop. 2025/26:293: sänkning till 14 år för allvarliga brott, tidsbegränsad fem år; omröstning väntas augusti 2026). Formulerad om verktyget, inte om brottslighetens orsaker. Omprövas efter riksdagens omröstning — antas förslaget blir frågan 'ska sänkningen behållas/permanentas?'."
        },
        {
          "id": "sq-lag-visitationszoner",
          "text": "Ska säkerhetszoner (visitationszoner) behållas som ett permanent verktyg för polisen?",
          "formulation_status": "verifierad",
          "fairness_note": "Använder lagens term (säkerhetszoner, införda april 2024) med vardagstermen inom parentes. Lagstiftningen ska utvärderas efter tre år, så permanentningen är ett levande vägval; varken 'trygghetsskapande' eller 'integritetskränkande' förekommer i frågan."
        }
      ]
    },
    {
      "id": "i-invandring-integration",
      "title": "Invandringen och integrationen",
      "slug": "invandringen-och-integrationen",
      "category": "migration",
      "status": "aktiv",
      "selection_sources": [
        {
          "institute": "Novus",
          "survey": "Viktigaste politiska frågan, juni 2026",
          "url": "https://novus.se/valjarforstaelse-arkiv/2026-06-viktigaste-politiska-fragan/",
          "date": "2026-06-08",
          "rank": 4,
          "share_percent": 45
        },
        {
          "institute": "SOM-institutet",
          "survey": "Nationella SOM-undersökningen 2025 (Svenska trender 1986–2025)",
          "url": "https://www.gu.se/sites/default/files/2026-03/Svenska%20trender%201986-2025.pdf",
          "date": "2026-03",
          "rank": 4,
          "share_percent": 23
        }
      ],
      "subquestions": [
        {
          "id": "sq-migration-miniminiva",
          "text": "Ska svensk asyllagstiftning ligga på EU-rättens miniminivå?",
          "formulation_status": "verifierad",
          "fairness_note": "Regelfråga med tydligt ja/nej som använder regelverkets egen term (EU-rättens miniminivå); formuleringen gör varken ja eller nej till det anständiga svaret, och blockets tre delfrågor täcker restriktiv och generös riktning likvärdigt."
        },
        {
          "id": "sq-migration-put",
          "text": "Ska permanenta uppehållstillstånd åter vara huvudregel?",
          "formulation_status": "verifierad",
          "fairness_note": "'Åter' är en faktisk beskrivning av rättsläget före 2021 års ändringar, inte en värdering."
        },
        {
          "id": "sq-migration-atervandring",
          "text": "Ska det statliga stödet till frivillig återvandring behållas?",
          "formulation_status": "verifierad",
          "fairness_note": "'Frivillig' och 'statligt stöd' är regelverkets egna termer; frågan mäter inställning till ordningen, inte till människor."
        }
      ]
    },
    {
      "id": "i-aldreomsorgen",
      "title": "Äldreomsorgen",
      "slug": "aldreomsorgen",
      "category": "välfärd",
      "status": "aktiv",
      "selection_sources": [
        {
          "institute": "Novus",
          "survey": "Viktigaste politiska frågan, juni 2026",
          "url": "https://novus.se/valjarforstaelse-arkiv/2026-06-viktigaste-politiska-fragan/",
          "date": "2026-06-08",
          "rank": 5,
          "share_percent": 42
        },
        {
          "institute": "SOM-institutet",
          "survey": "Nationella SOM-undersökningen 2025 (Svenska trender 1986–2025)",
          "url": "https://www.gu.se/sites/default/files/2026-03/Svenska%20trender%201986-2025.pdf",
          "date": "2026-03",
          "rank": null,
          "share_percent": null,
          "note": "Kategorin 'äldrefrågor' ingår bland de 15 största kategorierna i SOM:s tabell över viktigaste frågor/samhällsproblem 2025."
        }
      ],
      "subquestions": [
        {
          "id": "sq-aldre-bemanning",
          "text": "Ska det införas en nationell bemanningsnorm för äldreomsorgen?",
          "formulation_status": "verifierad",
          "fairness_note": "Mäter inställningen till en nationell bemanningsnorm som sådan, inte till en viss mekanism (lag, statsbidrag eller föreskrift) — annars skulle partier som vill ha normen men inte specificerar hur filtreras bort som falsk tystnad. Båda svaren är likvärdigt försvarbara: ja som nationell garanti, nej som kommunalt självstyre; inget framställs som omsorgssvikt."
        },
        {
          "id": "sq-aldre-sprakkrav",
          "text": "Ska det ställas krav på kunskaper i svenska för personal i äldreomsorgen?",
          "formulation_status": "verifierad",
          "fairness_note": "Mäter inställningen till svenskkrav som sådant, inte till en viss mekanism (lag, föreskrift, arbetsgivarkrav eller bidragsvillkor) — mekanism-kravet 'lagstadgas' fällde annars partier som uttalat vill ha språkkrav men inte specificerar hur, som falsk tystnad. Frågan värderar inte personalgrupper utan mäter inställning till kravet; både ja och nej är sakligt försvarbara."
        }
      ]
    },
    {
      "id": "i-klimat-miljo",
      "title": "Klimatet och miljön",
      "slug": "klimatet-och-miljon",
      "category": "klimat-miljö",
      "status": "aktiv",
      "selection_sources": [
        {
          "institute": "Novus",
          "survey": "Viktigaste politiska frågan, juni 2026",
          "url": "https://novus.se/valjarforstaelse-arkiv/2026-06-viktigaste-politiska-fragan/",
          "date": "2026-06-08",
          "rank": 6,
          "share_percent": 38,
          "note": "Novus mäter klimatet (plats 6, 38 %) och miljön (plats 9, 34 %) separat; kategorierna slås ihop till en fråga i registret, i linje med sajtens kategori klimat-miljö. Miljöns uppgång (+5) var mätningens enda statistiskt säkerställda förändring."
        },
        {
          "institute": "SOM-institutet",
          "survey": "Nationella SOM-undersökningen 2025 (Svenska trender 1986–2025)",
          "url": "https://www.gu.se/sites/default/files/2026-03/Svenska%20trender%201986-2025.pdf",
          "date": "2026-03",
          "rank": 5,
          "share_percent": 19,
          "note": "SOM redovisar den kombinerade kategorin miljö/energi."
        }
      ],
      "subquestions": [
        {
          "id": "sq-klimat-nettonoll",
          "text": "Ska Sveriges mål om nettonollutsläpp till 2045 ligga fast?",
          "formulation_status": "verifierad",
          "fairness_note": "'Ligga fast' mäter åtagandet till ett beslutat mål; både skärpning och uppluckring landar i nej-/villkorat-svar som citaten får precisera."
        },
        {
          "id": "sq-klimat-reduktionsplikt",
          "text": "Ska reduktionsplikten på drivmedel (i dag 10 procent) höjas under mandatperioden 2027–2030?",
          "formulation_status": "verifierad",
          "fairness_note": "Förankrad i beslutad ordning (10 procent för bensin och diesel sedan 1 juli 2025, låst t.o.m. 2030 om inte riksdagen beslutar annat). Konkret styrmedelsfråga; nivåord som 'ambitiös' eller 'dyr' förekommer inte."
        }
      ]
    },
    {
      "id": "i-jobben",
      "title": "Jobben och arbetsmarknaden",
      "slug": "jobben-och-arbetsmarknaden",
      "category": "övrigt",
      "status": "aktiv",
      "selection_sources": [
        {
          "institute": "Novus",
          "survey": "Viktigaste politiska frågan, juni 2026",
          "url": "https://novus.se/valjarforstaelse-arkiv/2026-06-viktigaste-politiska-fragan/",
          "date": "2026-06-08",
          "rank": 7,
          "share_percent": 37
        },
        {
          "institute": "SOM-institutet",
          "survey": "Nationella SOM-undersökningen 2025 (Svenska trender 1986–2025)",
          "url": "https://www.gu.se/sites/default/files/2026-03/Svenska%20trender%201986-2025.pdf",
          "date": "2026-03",
          "rank": null,
          "share_percent": null,
          "note": "Kategorin 'arbetsmarknad' ingår bland de 15 största kategorierna i SOM:s tabell över viktigaste frågor/samhällsproblem 2025."
        }
      ],
      "subquestions": [
        {
          "id": "sq-jobb-akassa",
          "text": "Ska taket i a-kassan (i dag 34 000 kronor i månaden för 80 procents ersättning) höjas?",
          "formulation_status": "verifierad",
          "fairness_note": "Förankrad i beslutad ordning (nya inkomstbaserade a-kassan sedan 1 oktober 2025). Konkret nivåfråga utan värdering av arbetslinje eller trygghetslinje — de ramarna får partiernas citat stå för."
        },
        {
          "id": "sq-jobb-lonegolv",
          "text": "Ska lönekravet för arbetskraftsinvandring behållas på minst dagens nivå (90 procent av medianlönen)?",
          "formulation_status": "verifierad",
          "fairness_note": "Symmetrisk kring beslutad ordning (90 procent av medianlönen sedan 1 juni 2026, riksdagsbeslut mars 2026): ja täcker behålla eller skärpa, nej täcker sänka eller avskaffa — inget av svaren framställs som det ansvarsfulla. Ersätter tidigare 'höjas ytterligare?' som bara fångade ena riktningen."
        }
      ]
    },
    {
      "id": "i-ekonomin",
      "title": "Ekonomin",
      "slug": "ekonomin",
      "category": "skatter",
      "status": "aktiv",
      "selection_sources": [
        {
          "institute": "Novus",
          "survey": "Viktigaste politiska frågan, juni 2026",
          "url": "https://novus.se/valjarforstaelse-arkiv/2026-06-viktigaste-politiska-fragan/",
          "date": "2026-06-08",
          "rank": 8,
          "share_percent": 36,
          "note": "Novus kategori: 'Landets ekonomi'."
        },
        {
          "institute": "SOM-institutet",
          "survey": "Nationella SOM-undersökningen 2025 (Svenska trender 1986–2025)",
          "url": "https://www.gu.se/sites/default/files/2026-03/Svenska%20trender%201986-2025.pdf",
          "date": "2026-03",
          "rank": null,
          "share_percent": null,
          "note": "Kategorin 'ekonomi' ingår bland de 15 största kategorierna i SOM:s tabell över viktigaste frågor/samhällsproblem 2025."
        }
      ],
      "subquestions": [
        {
          "id": "sq-ekonomi-matmoms",
          "text": "Ska den tillfälligt sänkta matmomsen (6 procent till och med 31 december 2027) göras permanent?",
          "formulation_status": "verifierad",
          "fairness_note": "Förankrad i beslutad ordning (sänkt 12→6 procent 1 april 2026, tidsbegränsad t.o.m. 2027 — Skatteverket): frågan är ett äkta vägval före valdagen. Hushållsnära och binärt besvarbar; 'tillfälligt sänkta' är saklig beskrivning, inte värdering."
        },
        {
          "id": "sq-ekonomi-inkomstskatt",
          "text": "Ska den statliga inkomstskatten sänkas under mandatperioden?",
          "formulation_status": "verifierad",
          "fairness_note": "Avgränsad till en namngiven skatt med tydliga ja- och nej-läger; ingen värdering av fördelningseffekter i frågan."
        }
      ]
    },
    {
      "id": "i-energipolitiken",
      "title": "Energipolitiken",
      "slug": "energipolitiken",
      "category": "klimat-miljö",
      "status": "aktiv",
      "selection_sources": [
        {
          "institute": "Novus",
          "survey": "Viktigaste politiska frågan, juni 2026",
          "url": "https://novus.se/valjarforstaelse-arkiv/2026-06-viktigaste-politiska-fragan/",
          "date": "2026-06-08",
          "rank": 10,
          "share_percent": 31,
          "note": "Ny i topp 10 i juni 2026; Novus kopplar uppgången till elpriserna och omvärldsläget."
        },
        {
          "institute": "SOM-institutet",
          "survey": "Nationella SOM-undersökningen 2025 (Svenska trender 1986–2025)",
          "url": "https://www.gu.se/sites/default/files/2026-03/Svenska%20trender%201986-2025.pdf",
          "date": "2026-03",
          "rank": 5,
          "share_percent": 19,
          "note": "SOM redovisar den kombinerade kategorin miljö/energi."
        }
      ],
      "subquestions": [
        {
          "id": "sq-energi-karnkraft",
          "text": "Ska staten fortsätta finansiera utbyggnad av ny kärnkraft?",
          "formulation_status": "verifierad",
          "fairness_note": "'Fortsätta finansiera' mäter åtagandet till en beslutad ordning (lagen om statligt stöd för investeringar i ny kärnkraft, 2025:587, i kraft sedan augusti 2025: statliga lån och differenskontrakt) — frågan är rakt besvarbar oavsett om partiet vill bygga ut eller avveckla, utan att något av svaren pekas ut som det kloka."
        },
        {
          "id": "sq-energi-vindveto",
          "text": "Ska det kommunala vetot mot ny vindkraft behållas?",
          "formulation_status": "verifierad",
          "fairness_note": "'Vetot' är den etablerade termen för rådande ordning; frågan värderar varken vindkraft eller självstyre."
        }
      ]
    },
    {
      "id": "i-forsvaret",
      "title": "Försvaret och säkerheten",
      "slug": "forsvaret-och-sakerheten",
      "category": "försvar",
      "status": "aktiv",
      "selection_sources": [
        {
          "institute": "Novus",
          "survey": "Viktigaste politiska frågan, juni 2026 (dokumenterar januarimätningens placering)",
          "url": "https://novus.se/valjarforstaelse-arkiv/2026-06-viktigaste-politiska-fragan/",
          "date": "2026-06-08",
          "rank": 8,
          "share_percent": 35,
          "note": "Kvalar in via tröghetsregeln: plats 8 i januari 2026 (35 %). I juni 2026 plats 11 (30 %) efter en statistiskt säkerställd nedgång (−5). Juni-rapporten är källa för båda placeringarna."
        },
        {
          "institute": "SOM-institutet",
          "survey": "Nationella SOM-undersökningen 2025 (Svenska trender 1986–2025)",
          "url": "https://www.gu.se/sites/default/files/2026-03/Svenska%20trender%201986-2025.pdf",
          "date": "2026-03",
          "rank": null,
          "share_percent": null,
          "note": "Kategorin 'utrikes-/försvarspolitik' ingår bland de 15 största kategorierna i SOM:s tabell över viktigaste frågor/samhällsproblem 2025."
        }
      ],
      "subquestions": [
        {
          "id": "sq-forsvar-varnplikt",
          "text": "Ska värnpliktsutbildningen utökas utöver redan beslutade nivåer (10 000 per år 2030, cirka 12 000 per år 2032–2035)?",
          "formulation_status": "verifierad",
          "fairness_note": "Förankrad i försvarsbeslutet 2025–2030: eftersom en upptrappning redan är beslutad skiljer bara 'utöver beslutade nivåer' positionerna — annars hade nästan alla svarat ja. Mäter inte 'försvarsvilja'."
        },
        {
          "id": "sq-forsvar-karnvapen",
          "text": "Ska Sverige i lag förbjuda kärnvapen på svenskt territorium?",
          "formulation_status": "verifierad",
          "fairness_note": "Omformulerad efter källkontroll: bred politisk enighet råder om att kärnvapen inte ska placeras i Sverige i fredstid, så den tidigare frågan ('tillåtas i fredstid?') hade inte skilt positionerna. Den verkliga skiljelinjen är om förbudet ska lagfästas — en konkret lagstiftningsfråga där varken ja eller nej framställs som det säkra svaret."
        }
      ]
    }
  ]
}
